.dockerignore
.gitattributes
.gitignore
CONTRIBUTING.md
Dockerfile
LICENSE
MANIFEST.in
NOTICE
README.md
RELEASES.md
codeship-services.yml
codeship-steps.yml
docker-compose.yml
requirements.txt
set_filters.sh
setup.cfg
setup.py
versioneer.py
deployment/jupyter_unsecure.json
deployment/run_notebook.sh
img/protein.png
img/selector.png
img/smallmol.png
nbmolviz/.gitignore
nbmolviz/__init__.py
nbmolviz/__main__.py
nbmolviz/_version.py
nbmolviz/colormaps.py
nbmolviz/install.py
nbmolviz/utils.py
nbmolviz/widget_utils.py
nbmolviz.egg-info/PKG-INFO
nbmolviz.egg-info/SOURCES.txt
nbmolviz.egg-info/dependency_links.txt
nbmolviz.egg-info/requires.txt
nbmolviz.egg-info/top_level.txt
nbmolviz/base/__init__.py
nbmolviz/base/base_widget.py
nbmolviz/base/mdt2json.py
nbmolviz/mdtconfig/__init__.py
nbmolviz/mdtconfig/compute.py
nbmolviz/mdtconfig/docker.py
nbmolviz/mdtconfig/images.py
nbmolviz/mdtconfig/interfaces.py
nbmolviz/mdtconfig/visualization.py
nbmolviz/methods/README.md
nbmolviz/methods/__init__.py
nbmolviz/methods/atomgroups.py
nbmolviz/methods/atoms.py
nbmolviz/methods/method.py
nbmolviz/methods/molecules.py
nbmolviz/methods/trajectory.py
nbmolviz/static/VERSION
nbmolviz/static/extension.js
nbmolviz/static/index.js
nbmolviz/static/index.js.map
nbmolviz/static/nbmolviz.css
nbmolviz/uielements/README.md
nbmolviz/uielements/__init__.py
nbmolviz/uielements/components.py
nbmolviz/uielements/configurator.py
nbmolviz/uielements/logwidget.py
nbmolviz/uielements/plotting.py
nbmolviz/viewers/README.md
nbmolviz/viewers/__init__.py
nbmolviz/viewers/common.py
nbmolviz/viewers/geometry_viewer.py
nbmolviz/viewers/graph_viewer.py
nbmolviz/viewers/orbital_viewer.py
nbmolviz/viewers/trajectory_viewer.py
nbmolviz/viewers/viewercontainer.py
nbmolviz/widgets/__init__.py
nbmolviz/widgets/components.py
nbmolviz/widgets/geombuilder.py
nbmolviz/widgets/parameterization.py
nbmolviz/widgets/selection.py
nbmolviz/widgets/symmetry.py
notebooks/strip_nb_output.py
tests/.dockerignore
tests/Dockerfile
tests/galileo/README.md
tests/galileo/package.json
tests/galileo/bin/galileo
tests/galileo/collector/test_notebooks.js
tests/galileo/nightwatch_config/globals.js
