Metadata-Version: 1.1
Name: nbmolviz
Version: 0.7.0
Summary: Notebook Molecular Visualization: ipywidgets-based molecular visualization for molecular structures
Home-page: http://moldesign.bionano.autodesk.com/
Author: Autodesk, Inc.
Author-email: moleculardesigntoolkit@autodesk.com
License: Apache 2.0
Keywords: jupyter,notebook,chemistry,widget,3D,visualization
Platform: UNKNOWN
Classifier: Development Status :: 4 - Beta
Classifier: Intended Audience :: Science/Research
Classifier: Intended Audience :: Developers
Classifier: Intended Audience :: Education
Classifier: License :: OSI Approved :: Apache Software License
Classifier: Programming Language :: Python :: 2.7
Classifier: Programming Language :: Python :: 2
Classifier: Programming Language :: Python :: 3.5
Classifier: Programming Language :: Python :: 3.6
Classifier: Programming Language :: Python :: 3
Classifier: Topic :: Scientific/Engineering :: Chemistry
Classifier: Topic :: Scientific/Engineering :: Visualization
Classifier: Operating System :: POSIX
Classifier: Operating System :: Unix
Classifier: Operating System :: MacOS
